nonebot_plugin_bottle/__init__.py
nonebot_plugin_bottle/config.py
nonebot_plugin_bottle/data_source.py
nonebot_plugin_bottle/exception.py
nonebot_plugin_bottle/migrations/01a750736ea0_add_like.py
nonebot_plugin_bottle/migrations/449e066410fd_init_db.py
nonebot_plugin_bottle/migrations/8c88e60a419b_add_approve.py
nonebot_plugin_bottle/model.py
nonebot_plugin_bottle/webui/__init__.py
nonebot_plugin_bottle/webui/api.py
nonebot_plugin_bottle/webui/data_source.py
nonebot_plugin_bottle/webui/dist/favicon.ico
nonebot_plugin_bottle/webui/dist/index.html
nonebot_plugin_bottle/webui/dist/static/css/app.dd33a03d.css
nonebot_plugin_bottle/webui/dist/static/css/chunk-1b0fcb10.b75f36eb.css
nonebot_plugin_bottle/webui/dist/static/css/chunk-35d8a019.709f3a12.css
nonebot_plugin_bottle/webui/dist/static/css/chunk-6d41cbb0.985d50e9.css
nonebot_plugin_bottle/webui/dist/static/css/chunk-afeb0628.3c7f5ad9.css
nonebot_plugin_bottle/webui/dist/static/css/chunk-c32fde16.328c31e8.css
nonebot_plugin_bottle/webui/dist/static/css/chunk-elementUI.68c70ad5.css
nonebot_plugin_bottle/webui/dist/static/css/chunk-libs.3dfb7769.css
nonebot_plugin_bottle/webui/dist/static/fonts/element-icons.535877f5.woff
nonebot_plugin_bottle/webui/dist/static/fonts/element-icons.732389de.ttf
nonebot_plugin_bottle/webui/dist/static/img/404.a57b6f31.png
nonebot_plugin_bottle/webui/dist/static/img/404_cloud.0f4bc32b.png
nonebot_plugin_bottle/webui/dist/static/js/app.e7b80f2b.js
nonebot_plugin_bottle/webui/dist/static/js/chunk-1b0fcb10.9d7b6104.js
nonebot_plugin_bottle/webui/dist/static/js/chunk-2d2250de.0f7c8a37.js
nonebot_plugin_bottle/webui/dist/static/js/chunk-35d8a019.ecaaed98.js
nonebot_plugin_bottle/webui/dist/static/js/chunk-6d41cbb0.c9ba9cd6.js
nonebot_plugin_bottle/webui/dist/static/js/chunk-6edd168e.ed0dc9ec.js
nonebot_plugin_bottle/webui/dist/static/js/chunk-afeb0628.b960c23a.js
nonebot_plugin_bottle/webui/dist/static/js/chunk-c32fde16.5d5ee5ba.js
nonebot_plugin_bottle-2.1.1.0.dist-info/LICENCE
nonebot_plugin_bottle-2.1.1.0.dist-info/METADATA
nonebot_plugin_bottle-2.1.1.0.dist-info/WHEEL
nonebot_plugin_bottle-2.1.1.0.dist-info/RECORD
