Metadata-Version: 2.3
Name: nonebot_plugin_bottle
Version: 2.1.1.0
Summary: Bottle post plugin in Nonebot
License: GNU GPLv3
Author: Todysheep
Author-email: todysheep@163.com
Requires-Python: >=3.8,<4.0
Classifier: License :: Other/Proprietary License
Classifier: Programming Language :: Python :: 3
Classifier: Programming Language :: Python :: 3.8
Classifier: Programming Language :: Python :: 3.9
Classifier: Programming Language :: Python :: 3.10
Classifier: Programming Language :: Python :: 3.11
Classifier: Programming Language :: Python :: 3.12
Classifier: Programming Language :: Python :: 3.13
Requires-Dist: aiofiles (>=0.8.0)
Requires-Dist: httpx (>=0.23.0,<0.28.0)
Requires-Dist: jinja2 (>=3.1.4,<4.0.0)
Requires-Dist: nonebot-adapter-onebot (>=2.2.0)
Requires-Dist: nonebot-plugin-datastore (>=0.6.0)
Requires-Dist: nonebot2[fastapi] (>=2.0.0)
Requires-Dist: passlib[bcrypt] (>=1.7.4)
Requires-Dist: python-jose[cryptography] (>=3.3.0)
Project-URL: Homepage, https://github.com/Todysheep/nonebot_plugin_bottle
Project-URL: Repository, https://github.com/Todysheep/nonebot_plugin_bottle
